whiplash/__init__.py
whiplash/api/__init__.py
whiplash/api/client/__init__.py
whiplash/api/client/api_config.py
whiplash/api/client/collection.py
whiplash/api/client/vector.py
whiplash/api/client/whiplash.py
whiplash/api/collections.py
whiplash/api/items.py
whiplash/api/projects.py
whiplash/collection.py
whiplash/collection_config.py
whiplash/dynamo_util.py
whiplash/embed.py
whiplash/hashing.py
whiplash/random.py
whiplash/responses.py
whiplash/storage.py
whiplash/vector.py
whiplash/vector_math.py
whiplash/whiplash.py
whiplash_client-0.1.1.dist-info/LICENSE
whiplash_client-0.1.1.dist-info/METADATA
whiplash_client-0.1.1.dist-info/WHEEL
whiplash_client-0.1.1.dist-info/RECORD
