Metadata-Version: 2.1
Name: whiplash-client
Version: 0.1.1
Summary: Blazing-fast lightweight vector store on top of DynamoDB
License: MIT
Author: Eric Mills
Author-email: ericmills2@gmail.com
Requires-Python: >=3.11,<4.0
Classifier: License :: OSI Approved :: MIT License
Classifier: Programming Language :: Python :: 3
Classifier: Programming Language :: Python :: 3.11
Requires-Dist: boto3 (>=1.28.17,<2.0.0)
Requires-Dist: numpy (>=1.25.2,<2.0.0)
Requires-Dist: xxhash (>=3.3.0,<4.0.0)
